peanut_pkg/__init__.py
peanut_pkg/peanut_sort.py
peanut_pkg-2.5.dist-info/METADATA
peanut_pkg-2.5.dist-info/WHEEL
peanut_pkg-2.5.dist-info/top_level.txt
peanut_pkg-2.5.dist-info/RECORD
