Metadata-Version: 2.1
Name: peanut-pkg
Version: 2.5
Summary: peanut_pkg module
Home-page: https://github.com/jjun4341/peanut_sort/tree/ver2.0
Author: peanut
Author-email: jjun4341@naver.com
License: UNKNOWN
Download-URL: https://github.com/jjun4341/peanut_sort/tree/ver2.0
Keywords: sort
Platform: UNKNOWN
Classifier: Programming Language :: Python :: 3
Classifier: Programming Language :: Python :: 3.2
Classifier: Programming Language :: Python :: 3.3
Classifier: Programming Language :: Python :: 3.4
Classifier: Programming Language :: Python :: 3.5
Classifier: Programming Language :: Python :: 3.6
Classifier: Programming Language :: Python :: 3.7
Requires-Python: >=3
